automate/__init__.py
automate/cli.py
automate/core.py
automatexpertise-1.1.5.dist-info/METADATA
automatexpertise-1.1.5.dist-info/WHEEL
automatexpertise-1.1.5.dist-info/entry_points.txt
automatexpertise-1.1.5.dist-info/top_level.txt
automatexpertise-1.1.5.dist-info/RECORD
