Metadata-Version: 2.1
Name: automatexpertise
Version: 1.1.5
Summary: Utilitaire qui permet de d'automatiser l'initialisation d'AutomateXpertise
Home-page: UNKNOWN
Author: sKillseries
License: UNKNOWN
Platform: UNKNOWN
Requires-Python: >=3.9, <4
Requires-Dist: click (~=8.0.3)
Requires-Dist: docker
Requires-Dist: psutil (~=5.9.5)
